aliasedkeys/__init__.py
aliasedkeys-0.1.1.dist-info/LICENSE
aliasedkeys-0.1.1.dist-info/METADATA
aliasedkeys-0.1.1.dist-info/WHEEL
aliasedkeys-0.1.1.dist-info/RECORD
