Metadata-Version: 2.1
Name: aliasedkeys
Version: 0.1.1
Summary: 
Author: Matthew Young
Author-email: myoung.space.science@gmail.com
Requires-Python: >=3.10,<4.0
Classifier: Programming Language :: Python :: 3
Classifier: Programming Language :: Python :: 3.10
Classifier: Programming Language :: Python :: 3.11
Classifier: Programming Language :: Python :: 3.12
Requires-Dist: nonstring (>=0.1.0)
